local_env_vars/__init__.py
local_env_vars/env.py
local_env_vars-1.0.0.dist-info/LICENSE
local_env_vars-1.0.0.dist-info/METADATA
local_env_vars-1.0.0.dist-info/WHEEL
local_env_vars-1.0.0.dist-info/top_level.txt
local_env_vars-1.0.0.dist-info/RECORD
