Metadata-Version: 2.1
Name: local-env-vars
Version: 1.0.0
Summary: A simple local environmental variable manager
Home-page: https://github.com/JMSchietekat/local-env-vars
Author: Justin Schietekat
Author-email: justinschietekat@gmail.com
License: UNKNOWN
Project-URL: Bug Tracker, https://github.com/JMSchietekat/local-env-vars/issues
Platform: UNKNOWN
Classifier: Programming Language :: Python :: 3
Classifier: License :: OSI Approved :: MIT License
Classifier: Operating System :: OS Independent
Requires-Python: >=3.6
License-File: LICENSE
